{
  "environments": {
    "dev": {
      "name": "DEV",
      "url": "https://yourorg-dev.crm.dynamics.com",
      "publisherPrefix": "abc",
      "description": "Development environment - Update URL and prefix before use"
    },
    "pp": {
      "name": "PP",
      "url": "https://yourorg-pp.crm.dynamics.com",
      "publisherPrefix": "abc",
      "description": "Pre-production environment - Update URL and prefix before use"
    },
    "prod": {
      "name": "PROD",
      "url": "https://yourorg.crm.dynamics.com",
      "publisherPrefix": "abc",
      "description": "Production environment - Update URL and prefix before use"
    }
  },
  "instructions": {
    "note": "This file is for reference only. Actual authentication is done via pac CLI.",
    "setup": [
      "1. Update the URLs above to match your actual Dataverse environments",
      "2. Update publisherPrefix to match your organization's prefix",
      "3. Authenticate: pac auth create --url [environment-url] --name [name]",
      "4. Deploy using: npm run deploy:[env] or use the deploy-*.ps1 scripts"
    ]
  }
}
